MANIFEST.in
setup.py
chief/__init__.py
chief/version.py
chief.egg-info/PKG-INFO
chief.egg-info/SOURCES.txt
chief.egg-info/dependency_links.txt
chief.egg-info/entry_points.txt
chief.egg-info/requires.txt
chief.egg-info/top_level.txt