Metadata-Version: 1.1
Name: chief
Version: 0.1.0
Summary: an incredible python package
Home-page: https://github.com/someuser/somepackage
Author: Parham Negahdar
Author-email: pnegahdar@gmail.com
License: MIT
Platform: UNKNOWN
Classifier: Development Status :: 4 - Beta
Classifier: Intended Audience :: Developers
Classifier: License :: OSI Approved :: MIT License
Classifier: Natural Language :: English
Classifier: Operating System :: Unix
Classifier: Programming Language :: Python :: 2.7
Classifier: Operating System :: OS Independent
